csh/__init__.py
csh/cshldap.py
csh/member.py
csh/utils.py
csh/webnews.py
cshpy3-0.3.0.0a1.dev21.dist-info/DESCRIPTION.rst
cshpy3-0.3.0.0a1.dev21.dist-info/METADATA
cshpy3-0.3.0.0a1.dev21.dist-info/RECORD
cshpy3-0.3.0.0a1.dev21.dist-info/WHEEL
cshpy3-0.3.0.0a1.dev21.dist-info/metadata.json
cshpy3-0.3.0.0a1.dev21.dist-info/pbr.json
cshpy3-0.3.0.0a1.dev21.dist-info/top_level.txt
