Metadata-Version: 2.0
Name: cshpy3
Version: 0.3.0.0a1.dev21
Summary: A collection of Python 3 utilities and wrappers for services run by Computer Science House at RIT
Home-page: UNKNOWN
Author: Steven Mirabito
Author-email: smirabito@csh.rit.edu
License: MIT
Keywords: csh
Platform: UNKNOWN
Classifier: Natural Language :: English
Classifier: Operating System :: POSIX :: Linux
Classifier: Programming Language :: Python :: 3
Requires-Dist: gssapi (==1.1.4)
Requires-Dist: ldap3 (==1.0.3)
Requires-Dist: requests (==2.9.1)
